yaka_llm/__init__.py
yaka_llm/core.py
yaka_llm/open_ai.py
yaka_llm/py.typed
yaka_llm-1.0.1.dist-info/WHEEL
yaka_llm-1.0.1.dist-info/METADATA
yaka_llm-1.0.1.dist-info/RECORD
