Metadata-Version: 2.3
Name: yaka-llm
Version: 1.0.1
Summary: Faster and Smaller alternative to Lanchain
Author: StickyCoolDev
Author-email: StickyCoolDev <hujifa.info@gmaill.com>
Requires-Python: >=3.12
